setup.py
pyrple/__init__.py
pyrple.egg-info/PKG-INFO
pyrple.egg-info/SOURCES.txt
pyrple.egg-info/dependency_links.txt
pyrple.egg-info/not-zip-safe
pyrple.egg-info/top_level.txt