Metadata-Version: 1.0
Name: pyrple
Version: 0.1
Summary: Python wrapper to make simple get requests with the Purple Wifi API.
Home-page: https://github.com/woblers/pyrple
Author: Toby Petty
Author-email: me@tobypetty.com
License: MIT
Platform: UNKNOWN
